<?xml version="1.0" encoding="UTF-8"?>
<Configuration status="INFO">
    <Appenders>
        <!-- Console Appender for all logs except API logs -->
        <Console name="Console" target="SYSTEM_OUT">
            <PatternLayout>
                <pattern>%d{yyyy-MM-dd HH:mm:ss} %highlight{%-5level} [%t] %style{%C{1}}{cyan}: %msg%n%throwable</pattern>
                <disableAnsi>false</disableAnsi>
            </PatternLayout>
        </Console>

        <!-- Rolling File Appender for all logs -->
        <RollingFile name="RollingFile"
                     fileName="./logs/application.log"
                     filePattern="./logs/$${date:yyyy-MM}/application-%d{-dd-MMMM-yyyy}-%i.log.txt">
            <PatternLayout>
                <pattern>%d %p %C{1} [%t] %m%n</pattern>
            </PatternLayout>
            <Policies>
                <OnStartupTriggeringPolicy />
                <SizeBasedTriggeringPolicy size="10MB" />
                <TimeBasedTriggeringPolicy />
            </Policies>
        </RollingFile>

        <!-- Separate File Appender for API Logs -->
        <RollingFile name="ApiLogFile"
                     fileName="./logs/api-logs.log"
                     filePattern="./logs/$${date:yyyy-MM}/api-logs-%d{-dd-MMMM-yyyy}-%i.log.txt">
            <PatternLayout>
                <pattern>%d %p %C{1} [%t] %m%n</pattern>
            </PatternLayout>
            <Policies>
                <SizeBasedTriggeringPolicy size="10MB" />
                <TimeBasedTriggeringPolicy />
            </Policies>
        </RollingFile>

    </Appenders>

    <Loggers>
        <!-- Root Logger for General Logs (Console + Application Log File) -->
        <Root level="info">
            <AppenderRef ref="Console"/>
            <AppenderRef ref="RollingFile"/>
        </Root>

        <!-- Logger for Application-Specific Logs -->
        <Logger name="com.hcmus.sakila" level="trace" additivity="false">
            <AppenderRef ref="Console"/>
            <AppenderRef ref="RollingFile"/>
        </Logger>

        <!-- API Logger: Logs API requests and responses only to the file -->
        <Logger name="API_LOGGER" level="info" additivity="false">
            <AppenderRef ref="ApiLogFile"/>
        </Logger>
    </Loggers>
</Configuration>
